{
    "configurations": [
        {
            "name": "Win32",
            "includePath": [
                "C:\\Users\\iclou\\AppData\\Local\\Arduino15\\packages\\esp32\\tools\\**",
                "C:\\Users\\iclou\\AppData\\Local\\Arduino15\\packages\\esp32\\hardware\\esp32\\1.0.4\\**",
                "C:\\Users\\iclou\\AppData\\Local\\Arduino15\\packages\\esp8266\\tools\\**",
                "C:\\Users\\iclou\\Documents\\Arduino\\libraries\\**",
                "C:\\Program Files (x86)\\Arduino\\libraries\\**",
                "C:\\Users\\iclou\\AppData\\Local\\Arduino15\\packages\\esp8266\\hardware\\esp8266\\2.7.4\\**"
            ],
            "forcedInclude": [],
            "defines": [
                "USBCON"
            ],
            "intelliSenseMode": "windows-msvc-x64",
            "compilerPath": "C:/Program Files (x86)/Microsoft Visual Studio/2019/Community/VC/Tools/MSVC/14.27.29110/bin/Hostx64/x64/cl.exe",
            "cStandard": "c17",
            "cppStandard": "c++17"
        }
    ],
    "version": 4
}